fastapi_csv/__init__.py
fastapi_csv/applications.py
fastapi_csv/cli.py
fastapi_csv-0.1.0.dist-info/LICENSE
fastapi_csv-0.1.0.dist-info/METADATA
fastapi_csv-0.1.0.dist-info/WHEEL
fastapi_csv-0.1.0.dist-info/entry_points.txt
fastapi_csv-0.1.0.dist-info/top_level.txt
fastapi_csv-0.1.0.dist-info/RECORD
