Metadata-Version: 2.1
Name: fastapi-csv
Version: 0.1.0
Summary: Create APIs from CSV files within seconds, using fastapi
Home-page: https://github.com/jrieke/fastapi-csv
Author: Johannes Rieke
Author-email: johannes.rieke@gmail.com
License: MIT
Platform: UNKNOWN
Classifier: Programming Language :: Python :: 3
Classifier: Programming Language :: Python :: 3.6
Classifier: Programming Language :: Python :: 3.7
Classifier: Programming Language :: Python :: 3.8
Classifier: Operating System :: OS Independent
Classifier: License :: OSI Approved :: MIT License
Classifier: Intended Audience :: Developers
Requires-Python: >=3.6
